{
    "projectId": "67af85a600368d7c97b6",
    "projectName": "CodeCell",
    "settings": {
        "services": {
            "account": true,
            "avatars": true,
            "databases": true,
            "locale": true,
            "health": true,
            "storage": true,
            "teams": true,
            "users": true,
            "functions": true,
            "graphql": true,
            "messaging": true
        },
        "auth": {
            "methods": {
                "jwt": true,
                "phone": true,
                "invites": true,
                "anonymous": true,
                "email-otp": true,
                "magic-url": true,
                "email-password": true
            },
            "security": {
                "duration": 31536000,
                "limit": 0,
                "sessionsLimit": 10,
                "passwordHistory": 0,
                "passwordDictionary": false,
                "personalDataCheck": false,
                "sessionAlerts": false,
                "mockNumbers": []
            }
        }
    },
    "databases": [
        {
            "$id": "main-codecell",
            "name": "main-codecell",
            "enabled": true
        }
    ],
    "buckets": [
        {
            "$id": "question-attachment",
            "$permissions": [
                "create(\"users\")",
                "read(\"any\")",
                "read(\"users\")",
                "update(\"users\")",
                "delete(\"users\")"
            ],
            "fileSecurity": false,
            "name": "question-attachment",
            "enabled": true,
            "maximumFileSize": 50000000,
            "allowedFileExtensions": [
                "jpg",
                "jpeg",
                "png",
                "gif",
                "webp",
                "heic"
            ],
            "compression": "none",
            "encryption": true,
            "antivirus": true
        }
    ]
}